setup.py
ggT3.egg-info/PKG-INFO
ggT3.egg-info/SOURCES.txt
ggT3.egg-info/dependency_links.txt
ggT3.egg-info/entry_points.txt
ggT3.egg-info/not-zip-safe
ggT3.egg-info/requires.txt
ggT3.egg-info/top_level.txt
src/__init__.py
src/mcloud.py