Metadata-Version: 2.1
Name: ggT3
Version: 1.0.0
Summary: Demo Package for GfG Article.
Home-page: UNKNOWN
License: MIT
Keywords: python
Platform: UNKNOWN
Classifier: Programming Language :: Python :: 3
Classifier: License :: OSI Approved :: MIT License
Classifier: Operating System :: OS Independent
